glaider_fuzz/__init__.py
glaider_fuzz/__main__.py
glaider_fuzz/app_config.py
glaider_fuzz/attack_config.py
glaider_fuzz/attack_loader.py
glaider_fuzz/attack_registry.py
glaider_fuzz/chat_clients.py
glaider_fuzz/cli.py
glaider_fuzz/client_config.py
glaider_fuzz/interactive_chat.py
glaider_fuzz/interactive_mode.py
glaider_fuzz/langchain_integration.py
glaider_fuzz/logo.py
glaider_fuzz/prompt_injection_fuzzer.py
glaider_fuzz/ps_logging.py
glaider_fuzz/results_table.py
glaider_fuzz/test_base.py
glaider_fuzz/util.py
glaider_fuzz/work_progress_pool.py
glaider_fuzz/attack_data/custom_benchmark1.csv
glaider_fuzz/attack_data/harmful_behavior.csv
glaider_fuzz/attack_data/prompt_injections_for_base64.parquet
glaider_fuzz/attacks/__init__.py
glaider_fuzz/attacks/aim.py
glaider_fuzz/attacks/base64_injection.py
glaider_fuzz/attacks/complimentary_transition.py
glaider_fuzz/attacks/custom_benchmark.py
glaider_fuzz/attacks/dan.py
glaider_fuzz/attacks/dynamic_test.py
glaider_fuzz/attacks/ethical_compliance.py
glaider_fuzz/attacks/harmful_behavior.py
glaider_fuzz/attacks/self_refine.py
glaider_fuzz/attacks/translation.py
glaider_fuzz/attacks/typoglycemia.py
glaider_fuzz/attacks/ucar.py
glaider_fuzz/attacks/utils.py
tests/__init__.py
tests/test_chat_clients.py
tests/test_is_response_list.py
glaider_fuzzer-0.0.6.dist-info/LICENSE
glaider_fuzzer-0.0.6.dist-info/METADATA
glaider_fuzzer-0.0.6.dist-info/WHEEL
glaider_fuzzer-0.0.6.dist-info/entry_points.txt
glaider_fuzzer-0.0.6.dist-info/top_level.txt
glaider_fuzzer-0.0.6.dist-info/RECORD
